Workbook

Sheet Fortune500
A1: Company_Name | B1: Ticker | C1: Avg_PURPOSE | D1: Avg_PHYGITAL | E1: Avg_PLATFORMS | F1: Avg_PARTICIPATION | G1: Avg_PARTNERSHIPS | H1: Avg_PEOPLE | I1: Avg_AI_Intensity
A2: 3M | B2: MMM | C2: 3.3675 | D2: 0 | E2: 0.89 | F2: 0 | G2: 0.3875 | H2: 0.8225 | I2: =VLOOKUP(B2,Data!B:K,10,FALSE) -> 0.6563
A3: A-Mark Precious Metals | B3: AMRK | C3: 5.3866667 | D3: 0 | E3: 4.2633333 | F3: 0 | G3: 6.0366667 | H3: 6.2366667 | I3: =VLOOKUP(B3,Data!B:K,10,FALSE) -> #N/A
A4: ABM Industries | B4: ABM | C4: 6.5366667 | D4: 0 | E4: 0.47666667 | F4: 0 | G4: 8.53 | H4: 23.21 | I4: =VLOOKUP(B4,Data!B:K,10,FALSE) -> 0.6582
A5: AECOM | B5: ACM | C5: 3.1566667 | D5: 0 | E5: 2.47 | F5: 0 | G5: 33.75 | H5: 13.246667 | I5: =VLOOKUP(B5,Data!B:K,10,FALSE) -> 0.5554
A6: AES | B6: AES | C6: 0.76 | D6: 0 | E6: 2.0466667 | F6: 3.8866667 | G6: 7.2 | H6: 2.4433333 | I6: =VLOOKUP(B6,Data!B:K,10,FALSE) -> 0.6606
A7: AGCO | B7: AGCO | C7: 4.9775 | D7: 0 | E7: 1.135 | F7: 2.935 | G7: 35.2725 | H7: 9.96 | I7: =VLOOKUP(B7,Data!B:K,10,FALSE) -> 0.566
A8: APA | B8: APA | C8: 4.98 | D8: 0 | E8: 1.12 | F8: 0 | G8: 5.355 | H8: 13.91 | I8: =VLOOKUP(B8,Data!B:K,10,FALSE) -> 0.6562
A9: ARKO | B9: ARKO | C9: 3.02 | D9: 0 | E9: 2.7725 | F9: 0 | G9: 0 | H9: 0.8825 | I9: =VLOOKUP(B9,Data!B:K,10,FALSE) -> 0.6443
A10: AT&T | B10: T | C10: 5.775 | D10: 11.2075 | E10: 2.4575 | F10: 31.6675 | G10: 1.75 | H10: 6.365 | I10: =VLOOKUP(B10,Data!B:K,10,FALSE) -> 0.6981
A11: AbbVie | B11: ABBV | C11: 2.55 | D11: 0 | E11: 1.2 | F11: 0 | G11: 18.905 | H11: 8.79 | I11: =VLOOKUP(B11,Data!B:K,10,FALSE) -> 0.6096
A12: Abbott Laboratories | B12: ABT | C12: 4.295 | D12: 0 | E12: 3.5825 | F12: 0 | G12: 1.0425 | H12: 3.7575 | I12: =VLOOKUP(B12,Data!B:K,10,FALSE) -> 0.6127
A13: Adobe | B13: ADBE | C13: 1.5775 | D13: 3.155 | E13: 13.395 | F13: 7.06 | G13: 4.1775 | H13: 22.495 | I13: =VLOOKUP(B13,Data!B:K,10,FALSE) -> 0.734
... A469: Zoetis | B469: ZTS | C469: 5.875 | D469: 0 | E469: 1.535 | F469: 0 | G469: 2.7325 | H469: 3.215 | I469: =VLOOKUP(B469,Data!B:K,10,FALSE) -> 0.6283

Sheet Data
A1: company_name | B1: ticker | C1: cik | D1: universal_name | E1: country_forbes | F1: industry_forbes | G1: rank_forbes | H1: rank_fortune | I1: market_cap_yf | J1: company_profile | K1: ai_score_v2_avg | L1: ai_score_v2_min | M1: ai_score_v2_max | N1: filing_count
A2: Autodesk | B2: ADSK | C2: 769397 | D2: Autodesk | E2: United States | F2: IT Software & Services | G2: 1114 | I2: 46212481024 | J2: hybrid | K2: 0.8026 | L2: 0.8008 | M2: 0.8064 | N2: 16
A3: CoreWeave | B3: CRWV | C3: 1769628 | D3: CoreWeave | E3: United States | F3: IT Software & Services | G3: 1799 | I3: 47267246080 | J3: hybrid | K3: 0.8003 | L3: 0.8003 | M3: 0.8003 | N3: 3
A4: ZIM Integrated Shipping Services | B4: ZIM | C4: 1654126 | D4: ZIM Integrated Shipping Services | E4: Israel | F4: Transportation | G4: 1403 | I4: 3467971840 | J4: buyer | K4: 0.7941 | L4: 0.7555 | M4: 0.8072 | N4: 4
A5: Snowflake | B5: SNOW | C5: 1640147 | D5: Snowflake | E5: United States | F5: IT Software & Services | G5: 1619 | I5: 54352994304 | J5: hybrid | K5: 0.7803 | L5: 0.75 | M5: 0.8087 | N5: 16
A6: Roblox | B6: RBLX | C6: 1315098 | D6: Roblox | E6: United States | F6: IT Software & Services | G6: 1652 | I6: 43826380800 | J6: hybrid | K6: 0.7763 | L6: 0.75 | M6: 0.8051 | N6: 16
A7: AstraZeneca | B7: AZN | C7: 901832 | D7: AstraZeneca | E7: United Kingdom | F7: Drugs & Biotechnology | G7: 109 | I7: 318490247168 | J7: buyer | K7: 0.775 | L7: 0.75 | M7: 0.8 | N7: 4
A8: Microsoft | B8: MSFT | C8: 789019 | D8: Microsoft | E8: United States | F8: IT Software & Services | G8: 9 | H8: 14 | I8: 3048369291264 | J8: hybrid | K8: 0.7649 | L8: 0.75 | M8: 0.8105 | N8: 16
A9: JD.com | B9: JD | C9: 1549802 | D9: JD.com | E9: China | F9: Retailing | G9: 171 | I9: 40204816384 | J9: hybrid | K9: 0.7636 | L9: 0.763 | M9: 0.7645 | N9: 4
A10: Nu Holdings | B10: NU | C10: 1691493 | D10: Nu Holdings | E10: Cayman Islands | F10: Banking | G10: 546 | I10: 80388104192 | J10: buyer | K10: 0.7617 | L10: 0.7596 | M10: 0.7637 | N10: 4
A11: Bid | B11: BIDU | C11: 1329099 | D11: Baidu | E11: China | F11: IT Software & Services | G11: 403 | I11: 47117533184 | J11: hybrid | K11: 0.7572 | L11: 0.7538 | M11: 0.7605 | N11: 16
A12: FactSet Research Systems | B12: FDS | C12: 1013237 | D12: FactSet Research Systems | E12: United States | F12: Business Services & Supplies | G12: 1863 | I12: 7210073088 | J12: buyer | K12: 0.757 | L12: 0.75 | M12: 0.8044 | N12: 16
A13: Alibaba Group | B13: BABA | C13: 1577552 | D13: Alibaba Group | E13: China | F13: Retailing | G13: 33 | I13: 390184304640 | J13: hybrid | K13: 0.7565 | L13: 0.7 | M13: 0.8089 | N13: 4
A14: Dell Technologies | B14: DELL | C14: 1571996 | D14: Dell Technologies | E14: United States | F14: Technology Hardware & Equipment | G14: 183 | H14: 44 | I14: 81020502016 | J14: hybrid | K14: 0.7541 | L14: 0.75 | M14: 0.768 | N14: 16
A15: Check Point Software | B15: CHKP | C15: 1015922 | D15: Check Point Software | E15: Israel | F15: IT Software & Services | G15: 1386 | I15: 16655010816 | J15: hybrid | K15: 0.7534 | L15: 0.7513 | M15: 0.7554 | N15: 4
A16: PDD Holdings | B16: PDD | C16: 1737806 | D16: PDD Holdings | E16: Ireland | F16: Retailing | G16: 152 | I16: 151632429056 | J16: hybrid | K16: 0.7527 | L16: 0.7523 | M16: 0.753 | N16: 4
A17: Palo Alto Networks | B17: PANW | C17: 1327567 | D17: Palo Alto Networks | E17: United States | F17: IT Software & Services | G17: 761 | H17: 470 | I17: 117009268736 | J17: hybrid | K17: 0.7526 | L17: 0.75 | M17: 0.7633 | N17: 16
A18: Elbit Systems | B18: ESLT | C18: 1027664 | D18: Elbit Systems | E18: Israel | F18: Aerospace & Defense | G18: 1947 | I18: 34992005120 | J18: hybrid | K18: 0.7522 | L18: 0.751 | M18: 0.753 | N18: 4
A19: XP | B19: XP | C19: 1787425 | D19: XP | E19: Brazil | F19: Diversified Financials | G19: 1261 | I19: 11432478720 | J19: buyer | K19: 0.7518 | L19: 0.7515 | M19: 0.7524 | N19: 4
A20: Palantir Technologies | B20: PLTR | C20: 1321655 | D20: Palantir Technologies | E20: United States | F20: IT Software & Services | G20: 1347 | I20: 307747127296 | J20: hybrid | K20: 0.7514 | L20: 0.7 | M20: 0.8086 | N20: 16
A21: Zscaler | B21: ZS | C21: 1713683 | D21: Zscaler | E21: United States | F21: Business Services & Supplies | G21: 1746 | I21: 23139272704 | J21: hybrid | K21: 0.7514 | L21: 0.75 | M21: 0.7592 | N21: 16
A22: Datadog | B22: DDOG | C22: 1561550 | D22: Datadog | E22: United States | F22: IT Software & Services | G22: 1726 | I22: 37211426816 | J22: hybrid | K22: 0.7514 | L22: 0.75 | M22: 0.7574 | N22: 16
A23: CrowdStrike | B23: CRWD | C23: 1535527 | D23: CrowdStrike | E23: United States | F23: IT Software & Services | G23: 1490 | I23: 88746213376 | J23: hybrid | K23: 0.7513 | L23: 0.75 | M23: 0.7563 | N23: 16
A24: DocuSign | B24: DOCU | C24: 1261333 | D24: DocuSign | E24: United States | F24: IT Software & Services | G24: 1415 | I24: 8152101888 | J24: hybrid | K24: 0.7509 | L24: 0.75 | M24: 0.7538 | N24: 16
A25: Cloudflare | B25: NET | C25: 1477333 | D25: Cloudflare | E25: United States | F25: IT Software & Services | G25: 1671 | I25: 58209148928 | J25: hybrid | K25: 0.7507 | L25: 0.75 | M25: 0.7547 | N25: 16
A26: Lumen Technologies | B26: LUMN | C26: 18926 | D26: Lumen Technologies | E26: United States | F26: Telecommunications Services | G26: 1441 | H26: 325 | I26: 7608835072 | J26: hybrid | K26: 0.7506 | L26: 0.75 | M26: 0.7529 | N26: 16
A27: DoorDash | B27: DASH | C27: 1792789 | D27: DoorDash | E27: United States | F27: Transportation | G27: 1191 | H27: 394 | I27: 71157858304 | J27: hybrid | K27: 0.7506 | L27: 0.75 | M27: 0.7525 | N27: 16
A28: Deutsche Bank | B28: DB | C28: 1159508 | D28: Deutsche Bank | E28: Germany | F28: Diversified Financials | G28: 133 | I28: 69268037632 | J28: buyer | K28: 0.7506 | L28: 0.75 | M28: 0.7512 | N28: 4
A29: Copart | B29: CPRT | C29: 900075 | D29: Copart | E29: United States | F29: Retailing | G29: 1062 | I29: 34519511040 | J29: buyer | K29: 0.7503 | L29: 0.75 | M29: 0.7521 | N29: 16
A30: Shinhan Financial Group | B30: SHG | C30: 1263043 | D30: Shinhan Financial Group | E30: South Korea | F30: Banking | G30: 308 | J30: buyer | K30: 0.75 | L30: 0.75 | M30: 0.75 | N30: 4
A31: HubSpot | B31: HUBS | C31: 1404655 | D31: HubSpot | E31: United States | F31: IT Software & Services | G31: 1762 | I31: 11707872256 | J31: hybrid | K31: 0.7473 | L31: 0.7 | M31: 0.8004 | N31: 16
A32: AppLovin | B32: APP | C32: 1751008 | D32: AppLovin | E32: United States | F32: IT Software & Services | G32: 1007 | I32: 128452370432 | J32: hybrid | K32: 0.7442 | L32: 0.7 | M32: 0.8006 | N32: 16
A33: Wipro | B33: WIT | C33: 1123799 | D33: Wipro | E33: India | F33: IT Software & Services | G33: 901 | I33: 23401965568 | J33: buyer | K33: 0.7432 | L33: 0.7026 | M33: 0.7592 | N33: 4
A34: Sirius XM | B34: SIRI | C34: 908937 | D34: Sirius XM | E34: United States | F34: Media | G34: 1822 | H34: 448 | I34: 7030772224 | J34: hybrid | K34: 0.7422 | L34: 0.7 | M34: 0.7583 | N34: 16
A35: Synopsys | B35: SNPS | C35: 883241 | D35: Synopsys | E35: United States | F35: IT Software & Services | G35: 970 | I35: 80208240640 | J35: hybrid | K35: 0.7419 | L35: 0.7 | M35: 0.7556 | N35: 16
A36: Block | B36: XYZ | C36: 1512673 | D36: Block | E36: United States | F36: Banking | G36: 434 | H36: 179 | I36: 30695602176 | J36: hybrid | K36: 0.7389 | L36: 0.7 | M36: 0.756 | N36: 16
A37: Atlassian | B37: TEAM | C37: 1650372 | D37: Atlassian | E37: United States | F37: IT Software & Services | G37: 1588 | I37: 18715279360 | J37: hybrid | K37: 0.7379 | L37: 0.7 | M37: 0.8004 | N37: 14
A38: Fortinet | B38: FTNT | C38: 1262039 | D38: Fortinet | E38: United States | F38: IT Software & Services | G38: 1003 | I38: 58190245888 | J38: hybrid | K38: 0.7364 | L38: 0.7 | M38: 0.8092 | N38: 16
A39: Axon Enterprise | B39: AXON | C39: 1069183 | D39: Axon Enterprise | E39: United States | F39: Aerospace & Defense | G39: 1646 | I39: 33687754752 | J39: hybrid | K39: 0.7355 | L39: 0.7 | M39: 0.8015 | N39: 16
A40: Adobe | B40: ADBE | C40: 796343 | D40: Adobe | E40: United States | F40: IT Software & Services | G40: 340 | H40: 201 | I40: 103203733504 | J40: hybrid | K40: 0.734 | L40: 0.7 | M40: 0.7755 | N40: 16
A41: Intercontinental Exchange | B41: ICE | C41: 1571949 | D41: Intercontinental Exchange | E41: United States | F41: Diversified Financials | G41: 360 | H41: 361 | I41: 86957932544 | J41: hybrid | K41: 0.7328 | L41: 0.7 | M41: 0.7516 | N41: 16
A42: Samsara | B42: IOT | C42: 1642896 | D42: Samsara | E42: United States | F42: IT Software & Services | G42: 1946 | I42: 14402020352 | J42: hybrid | K42: 0.7324 | L42: 0.65 | M42: 0.8052 | N42: 16
A43: Expedia | B43: EXPE | C43: 1324424 | D43: Expedia | E43: United States | F43: Business Services & Supplies | G43: 808 | H43: 312 | I43: 23056773120 | J43: hybrid | K43: 0.7312 | L43: 0.7 | M43: 0.75 | N43: 16
A44: Infosys | B44: INFY | C44: 1067491 | D44: Infosys | E44: India | F44: IT Software & Services | G44: 562 | I44: 56963321856 | J44: buyer | K44: 0.7312 | L44: 0.704 | M44: 0.7582 | N44: 4
A45: NetEase | B45: NTES | C45: 1110646 | D45: NetEase | E45: China | F45: IT Software & Services | G45: 501 | I45: 75043536896 | J45: hybrid | K45: 0.7308 | L45: 0.7037 | M45: 0.8074 | N45: 4
A46: NetApp | B46: NTAP | C46: 1002047 | D46: NetApp | E46: United States | F46: Technology Hardware & Equipment | G46: 1276 | I46: 20044681216 | J46: hybrid | K46: 0.7295 | L46: 0.7 | M46: 0.8032 | N46: 16
A47: Gartner | B47: IT | C47: 749251 | D47: Gartner | E47: United States | F47: IT Software & Services | G47: 1146 | I47: 10644712448 | J47: buyer | K47: 0.7284 | L47: 0.7 | M47: 0.8031 | N47: 16
A48: Philip Morris | B48: PM | C48: 1413329 | D48: Philip Morris | E48: United States | F48: Food, Drink & Tobacco | G48: 179 | H48: 121 | I48: 288530563072 | J48: hybrid | K48: 0.7283 | L48: 0.65 | M48: 0.7508 | N48: 16
A49: Sony | B49: SONY | C49: 313838 | D49: Sony | E49: Japan | F49: Technology Hardware & Equipment | G49: 57 | I49: 131888955392 | J49: buyer | K49: 0.7275 | L49: 0.6506 | M49: 0.7557 | N49: 4
A50: Itau Unibanco Holding | B50: ITUB | C50: 1132597 | D50: Itau Unibanco Holding | E50: Brazil | F50: Banking | G50: 82 | I50: 102381813760 | J50: buyer | K50: 0.7264 | L50: 0.7137 | M50: 0.7635 | N50: 4
A51: Veeva Systems | B51: VEEV | C51: 1393052 | D51: Veeva Systems | E51: United States | F51: IT Software & Services | G51: 1321 | I51: 28646825984 | J51: hybrid | K51: 0.7258 | L51: 0.7 | M51: 0.8022 | N51: 16
A52: Trade Desk | B52: TTD | C52: 1671933 | D52: Trade Desk | E52: United States | F52: IT Software & Services | G52: 1838 | I52: 11939985408 | J52: hybrid | K52: 0.7255 | L52: 0.7 | M52: 0.7523 | N52: 16
A53: Globalfoundries | B53: GFS | C53: 1709048 | D53: Globalfoundries | E53: United States | F53: Semiconductors | G53: 1671 | I53: 25641932800 | J53: buyer | K53: 0.7254 | L53: 0.7005 | M53: 0.7505 | N53: 4
A54: CoStar Group | B54: CSGP | C54: 1057352 | D54: CoStar Group | E54: United States | F54: IT Software & Services | G54: 1728 | I54: 20551208960 | J54: hybrid | K54: 0.7252 | L54: 0.7 | M54: 0.751 | N54: 16
A55: HSBC Holdings | B55: HSBC | C55: 1089113 | D55: HSBC Holdings | E55: United Kingdom | F55: Banking | G55: 15 | I55: 304798334976 | J55: buyer | K55: 0.725 | L55: 0.7 | M55: 0.75 | N55: 4
A56: Workday | B56: WDAY | C56: 1327811 | D56: Workday | E56: United States | F56: IT Software & Services | G56: 1074 | H56: 455 | I56: 34002450432 | J56: hybrid | K56: 0.7246 | L56: 0.7 | M56: 0.7634 | N56: 16
A57: Hewlett Packard Enterprise | B57: HPE | C57: 1645590 | D57: Hewlett Packard Enterprise | E57: United States | F57: IT Software & Services | G57: 379 | H57: 143 | I57: 27384485888 | J57: hybrid | K57: 0.7227 | L57: 0.7012 | M57: 0.8101 | N57: 16
A58: Tyler Technologies | B58: TYL | C58: 860731 | D58: Tyler Technologies | E58: United States | F58: IT Software & Services | G58: 1942 | I58: 13722430464 | J58: hybrid | K58: 0.7226 | L58: 0.7 | M58: 0.7538 | N58: 16
A59: Synchrony Financial | B59: SYF | C59: 1601712 | D59: Synchrony Financial | E59: United States | F59: Business Services & Supplies | G59: 392 | H59: 178 | I59: 24826595328 | J59: buyer | K59: 0.7219 | L59: 0.65 | M59: 0.75 | N59: 16
A60: Agilent Technologies | B60: A | C60: 1090872 | D60: Agilent Technologies | E60: United States | F60: Health Care Equipment & Services | G60: 1133 | I60: 34569854976 | J60: hybrid | K60: 0.7204 | L60: 0.7 | M60: 0.7565 | N60: 16
A61: EchoStar | B61: SATS | C61: 1415404 | D61: EchoStar | E61: United States | F61: Telecommunications Services | G61: 1200 | H61: 273 | I61: 31201474560 | J61: hybrid | K61: 0.7202 | L61: 0.7 | M61: 0.753 | N61: 16
A62: Robinhood Markets | B62: HOOD | C62: 1783879 | D62: Robinhood Markets | E62: United States | F62: Diversified Financials | G62: 894 | I62: 64652292096 | J62: hybrid | K62: 0.7199 | L62: 0.7 | M62: 0.8046 | N62: 16
A63: Amazon | B63: AMZN | C63: 1018724 | D63: Amazon | E63: United States | F63: Retail and Wholesale | G63: 5 | H63: 2 | I63: 2545370267648 | J63: buyer | K63: 0.719 | L63: 0.7028 | M63: 0.7657 | N63: 16
A64: Flutter Entertainment | B64: FLUT | C64: 1635327 | D64: Flutter Entertainment | E64: United States | F64: Hotels, Restaurants & Leisure | G64: 967 | I64: 20362446848 | J64: hybrid | K64: 0.719 | L64: 0.7 | M64: 0.7513 | N64: 8
A65: ServiceNow | B65: NOW | C65: 1373715 | D65: ServiceNow | E65: United States | F65: IT Software & Services | G65: 645 | H65: 386 | I65: 105060589568 | J65: hybrid | K65: 0.7186 | L65: 0.7 | M65: 0.813 | N65: 16
A66: PayPal | B66: PYPL | C66: 1633917 | D66: PayPal | E66: United States | F66: Business Services & Supplies | G66: 238 | H66: 137 | I66: 38179278848 | J66: hybrid | K66: 0.7178 | L66: 0.7 | M66: 0.7593 | N66: 16
A67: Arista Networks | B67: ANET | C67: 1596532 | D67: Arista Networks | E67: United States | F67: Technology Hardware & Equipment | G67: 852 | I67: 160225148928 | J67: hybrid | K67: 0.717 | L67: 0.7 | M67: 0.756 | N67: 16
A68: Haleon | B68: HLN | C68: 1900304 | D68: Haleon | E68: United Kingdom | F68: Drugs & Biotechnology | G68: 524 | I68: 49674592256 | J68: buyer | K68: 0.7167 | L68: 0.7 | M68: 0.75 | N68: 3
A69: MSCI | B69: MSCI | C69: 1408198 | D69: MSCI | E69: United States | F69: Business Services & Supplies | G69: 1157 | I69: 40549052416 | J69: hybrid | K69: 0.7163 | L69: 0.7 | M69: 0.8044 | N69: 16
A70: Lam Research | B70: LRCX | C70: 707549 | D70: Lam Research | E70: United States | F70: Capital Goods | G70: 506 | H70: 295 | I70: 303532212224 | J70: hybrid | K70: 0.7161 | L70: 0.7 | M70: 0.75 | N70: 16
A71: Gen Digital | B71: GEN | C71: 849399 | D71: Gen Digital | E71: United States | F71: IT Software & Services | G71: 1665 | I71: 13191557120 | J71: hybrid | K71: 0.716 | L71: 0.7 | M71: 0.7525 | N71: 16
A72: Chunghwa Telecom | B72: CHT | C72: 1132924 | D72: Chunghwa Telecom | E72: Taiwan | F72: Telecommunications Services | G72: 1043 | I72: 33578504192 | J72: buyer | K72: 0.7154 | L72: 0.7016 | M72: 0.7537 | N72: 4
A73: Meta Platforms | B73: META | C73: 1326801 | D73: Meta Platforms | E73: United States | F73: IT Software & Services | G73: 20 | H73: 22 | I73: 1745949687808 | J73: hybrid | K73: 0.715 | L73: 0.7 | M73: 0.7608 | N73: 16
A74: Reddit | B74: RDDT | C74: 1713445 | D74: Reddit | E74: United States | F74: IT Software & Services | G74: 1978 | I74: 27671533568 | J74: hybrid | K74: 0.715 | L74: 0.7 | M74: 0.7549 | N74: 7
A75: Take-Two Interactive Software | B75: TTWO | C75: 946581 | D75: Take-Two Interactive Software | E75: United States | F75: IT Software & Services | G75: 1688 | I75: 36199952384 | J75: buyer | K75: 0.7147 | L75: 0.7017 | M75: 0.7511 | N75: 16
A76: GE HealthCare Technologies | B76: GEHC | C76: 1932393 | D76: GE HealthCare Technologies | E76: United States | F76: Health Care Equipment & Services | G76: 539 | H76: 219 | I76: 37986742272 | J76: hybrid | K76: 0.7132 | L76: 0.7 | M76: 0.7535 | N76: 12
A77: Tradeweb Markets | B77: TW | C77: 1758730 | D77: Tradeweb Markets | E77: United States | F77: Diversified Financials | G77: 1622 | I77: 25886410752 | J77: hybrid | K77: 0.713 | L77: 0.7 | M77: 0.7526 | N77: 16
A78: GSK | B78: GSK | C78: 1131399 | D78: GSK | E78: United Kingdom | F78: Drugs & Biotechnology | G78: 236 | I78: 119395213312 | J78: buyer | K78: 0.7128 | L78: 0.65 | M78: 0.75 | N78: 4
A79: KT | B79: KT | C79: 892450 | D79: KT | E79: South Korea | F79: Telecommunications Services | G79: 1284 | I79: 11555066880 | J79: buyer | K79: 0.7125 | L79: 0.7 | M79: 0.75 | N79: 4
A80: British American Tobacco | B80: BTI | C80: 1303523 | D80: British American Tobacco | E80: United Kingdom | F80: Food, Drink & Tobacco | G80: 184 | I80: 135796015104 | J80: buyer | K80: 0.7125 | L80: 0.7 | M80: 0.75 | N80: 4
A81: Barclays | B81: BCS | C81: 312069 | D81: Barclays | E81: United Kingdom | F81: Diversified Financials | G81: 134 | I81: 87420256256 | J81: buyer | K81: 0.7125 | L81: 0.7 | M81: 0.75 | N81: 4
A82: Cadence Design | B82: CDNS | C82: 813672 | D82: Cadence Design | E82: United States | F82: IT Software & Services | G82: 1107 | I82: 77017931776 | J82: hybrid | K82: 0.7105 | L82: 0.6 | M82: 0.7565 | N82: 16
A83: Vipshop Holdings | B83: VIPS | C83: 1529192 | D83: Vipshop Holdings | E83: China | F83: Retailing | G83: 1342 | I83: 8454949888 | J83: hybrid | K83: 0.7092 | L83: 0.7083 | M83: 0.7099 | N83: 4
A84: Super Micro Computer | B84: SMCI | C84: 1375365 | D84: Super Micro Computer | E84: United States | F84: Technology Hardware & Equipment | G84: 833 | H84: 292 | I84: 18757355520 | J84: hybrid | K84: 0.709 | L84: 0.65 | M84: 0.7632 | N84: 16
A85: Alphabet | B85: GOOG | C85: 1652044 | D85: Alphabet | E85: United States | F85: IT Software & Services | G85: 9 | H85: 7 | I85: 4119694409728 | J85: hybrid | K85: 0.7084 | L85: 0.65 | M85: 0.8107 | N85: 16
A86: Intuit | B86: INTU | C86: 896878 | D86: Intuit | E86: United States | F86: IT Software & Services | G86: 394 | H86: 258 | I86: 97968955392 | J86: hybrid | K86: 0.7074 | L86: 0.65 | M86: 0.8036 | N86: 16
A87: Cisco Systems | B87: CSCO | C87: 858877 | D87: Cisco Systems | E87: United States | F87: IT Software & Services | G87: 94 | H87: 83 | I87: 308363165696 | J87: hybrid | K87: 0.7071 | L87: 0.65 | M87: 0.7548 | N87: 16
A88: NatWest Group | B88: NWG | C88: 844150 | D88: NatWest Group | E88: United Kingdom | F88: Banking | G88: 156 | I88: 66160111616 | J88: buyer | K88: 0.7071 | L88: 0.6895 | M88: 0.7391 | N88: 4
A89: GoDaddy | B89: GDDY | C89: 1609711 | D89: GoDaddy | E89: United States | F89: Business Services & Supplies | G89: 1304 | I89: 12088677376 | J89: hybrid | K89: 0.707 | L89: 0.65 | M89: 0.7558 | N89: 16
A90: Micron Technology | B90: MU | C90: 723125 | D90: Micron Technology | E90: United States | F90: Semiconductors | G90: 228 | H90: 170 | I90: 473186598912 | J90: hybrid | K90: 0.7068 | L90: 0.7 | M90: 0.7561 | N90: 17
A91: Toyota Motor | B91: TM | C91: 1094517 | D91: Toyota Motor | E91: Japan | F91: Consumer Durables | G91: 14 | I91: 302086291456 | J91: buyer | K91: 0.7067 | L91: 0.7059 | M91: 0.7081 | N91: 4
A92: Snap-on | B92: SNA | C92: 91440 | D92: Snap-on | E92: United States | F92: Consumer Durables | G92: 1446 | I92: 19811237888 | J92: hybrid | K92: 0.7061 | L92: 0.6195 | M92: 0.7542 | N92: 16
A93: Applied Materials | B93: AMAT | C93: 6951 | D93: Applied Materials | E93: United States | F93: Capital Goods | G93: 300 | H93: 158 | I93: 297018490880 | J93: hybrid | K93: 0.7058 | L93: 0.7 | M93: 0.7633 | N93: 16
A94: Banco Bradesco | B94: BBD | C94: 1160330 | D94: Banco Bradesco | E94: Brazil | F94: Banking | G94: 237 | I94: 43735945216 | J94: buyer | K94: 0.7054 | L94: 0.705 | M94: 0.7058 | N94: 4
A95: Qualcomm | B95: QCOM | C95: 804328 | D95: Qualcomm | E95: United States | F95: Semiconductors | G95: 193 | H95: 117 | I95: 152345952256 | J95: buyer | K95: 0.7052 | L95: 0.7 | M95: 0.7589 | N95: 16
A96: Labcorp Holdings | B96: LH | C96: 920148 | D96: Labcorp Holdings | E96: United States | F96: Health Care Equipment & Services | G96: 1011 | H96: 328 | I96: 23605800960 | J96: hybrid | K96: 0.7047 | L96: 0.65 | M96: 0.8031 | N96: 16
A97: Salesforce | B97: CRM | C97: 1108524 | D97: Salesforce | E97: United States | F97: IT Software & Services | G97: 147 | H97: 120 | I97: 166961758208 | J97: hybrid | K97: 0.7044 | L97: 0.7 | M97: 0.75 | N97: 16
A98: Sanmina | B98: SANM | C98: 897723 | D98: Sanmina | H98: 489 | I98: 8016543232 | J98: hybrid | K98: 0.7044 | L98: 0.7 | M98: 0.7155 | N98: 16
A99: Tesla | B99: TSLA | C99: 1318605 | D99: Tesla | E99: United States | F99: Consumer Durables | G99: 69 | H99: 43 | I99: 1576546729984 | J99: hybrid | K99: 0.7043 | L99: 0.65 | M99: 0.7558 | N99: 16
A100: Celestica | B100: CLS | C100: 1030894 | D100: Celestica | E100: Canada | F100: Technology Hardware & Equipment | G100: 1922 | I100: 34087100416 | J100: buyer | K100: 0.7042 | L100: 0.7 | M100: 0.7083 | N100: 7
...
